falcon_json-0.0.1.dist-info/metadata.json
falcon_json-0.0.1.dist-info/DESCRIPTION.rst
falcon_json-0.0.1.dist-info/top_level.txt
falcon_json-0.0.1.dist-info/WHEEL
falcon_json-0.0.1.dist-info/METADATA
falcon_json-0.0.1.dist-info/RECORD
falcon_json/__init__.py
falcon_json/hooks.py
