Metadata-Version: 2.0
Name: falcon-json
Version: 0.0.1
Summary: Falcon JSON helpers
Home-page: https://github.com/matino/falcon-json
Author: Mateusz Czubak
Author-email: mczubak@gmail.com
License: Apache License 2.0
Keywords: falcon json api
Platform: UNKNOWN
Classifier: Development Status :: 5 - Production/Stable
Classifier: Intended Audience :: Developers
Classifier: Operating System :: OS Independent
Classifier: Programming Language :: Python
Classifier: Programming Language :: Python :: 2
Classifier: Programming Language :: Python :: 2.7
Classifier: Programming Language :: Python :: 3
Classifier: Programming Language :: Python :: 3.4
Classifier: Topic :: Software Development :: Libraries
Requires-Dist: falcon (>=0.3)
Requires-Dist: jsonschema (>=2.5.1)
